LICENSE
README.md
setup.cfg
setup.py
celebrity_births/__init__.py
celebrity_births/__main__.py
celebrity_births/celebrities_births.py
celebrity_births_package_ejb.egg-info/PKG-INFO
celebrity_births_package_ejb.egg-info/SOURCES.txt
celebrity_births_package_ejb.egg-info/dependency_links.txt
celebrity_births_package_ejb.egg-info/requires.txt
celebrity_births_package_ejb.egg-info/top_level.txt
test/__init__.py
test/test_celebrity_birth.py