Metadata-Version: 2.1
Name: celebrity-births-package-ejb
Version: 0.0.1
Summary: Mock package that allows you to find celebrity by date of birth
Home-page: https://github.com/IvanYingX/project_structure_pypi.git
Author: Blair Martin
License: MIT
Platform: UNKNOWN
License-File: LICENSE
